AmenablePDDL/__init__.py
AmenablePDDL/interface.py
AmenablePDDL-0.1.5.dist-info/LICENSE
AmenablePDDL-0.1.5.dist-info/METADATA
AmenablePDDL-0.1.5.dist-info/WHEEL
AmenablePDDL-0.1.5.dist-info/top_level.txt
AmenablePDDL-0.1.5.dist-info/RECORD
