Metadata-Version: 2.1
Name: AmenablePDDL
Version: 0.1.5
Summary: A high-level PDDL parsing and planning interface for implementing common classical planning algorithms. 
Home-page: https://github.com/juliusarolovitch/Amenable-PDDL
Author: Julius Arolovitch
Author-email: jarolovi@andrew.cmu.edu
Classifier: Programming Language :: Python :: 3.10
Classifier: License :: OSI Approved :: MIT License
Classifier: Operating System :: OS Independent
Requires-Python: >=3.9
License-File: LICENSE
Requires-Dist: pddl
Requires-Dist: lark-parser
Requires-Dist: typing-extensions
